{
  "uuid": "15e64b10-4e20-494d-b49d-9435ef6b45ff",
  "lastMigration": 28,
  "name": "7187 - Criando Apps Web com Angular e UiKit",
  "endpointPrefix": "v1",
  "latency": 0,
  "port": 3000,
  "hostname": "",
  "folders": [],
  "routes": [
    {
      "uuid": "3449e9cb-a3ab-44dc-9ec2-2ebdbbeef066",
      "type": "http",
      "documentation": "",
      "method": "get",
      "endpoint": "products",
      "responses": [
        {
          "uuid": "7832b2c6-7c57-4640-a9ee-7ef43e2eef70",
          "body": "[\n  {\n    \"_id\":\"481598b848f447b4b923ca2ad405aa09\",\n    \"title\":\"Cama M1 Urban\",\n    \"category\":\"accessories\",\n    \"description\":\"<ul><li><span><b>Pet:</b></span><span> Cachorros</span></li><li><span><b>Porte de Raça:</b></span><span> Grande, Médio e Pequeno</span></li><li><span><b>Idade:</b></span><span> Sênior, Adulto e Filhote</span></li><li><span><b>Material:</b></span><span> Plástico</span></li><li><span><b>Medidas<br>aproximadas:</b></span><span> Tamanho 8 (84 x 59,5 x h 25 cm), Tamanho 6 (70,5 x 52 x h 23,5 cm), Tamanho 4 (61,5 x 45 x h 21,5 cm), Tamanho 2 (52 x 36 x h 17,5 cm), Tamanho 12 (111 x 80,5 x h 33,5 cm), Tamanho 10 (93,5 x 68 x h 28 e5 cm)</span></li><li><span><b>Tipo:</b></span><span> Cama</span></li><li><span><b>Cor:</b></span><span> Bordô</span></li><li><span><b>Apresentação:</b></span><span> <p><span>Disponível nos tamanhos 2, 4, 6, 8, 10 e 12</span></p></span></li><li><span><b>Código de barras:</b></span><span> 8010690074689</span></li></ul>\",        \n    \"price\":5999,\n    \"images\":[\"https://images.petz.com.br/fotos/1525443192336.jpg\"]    \n  },\n  {\n    \"_id\":\"481598b848f447b4b923ca2ad405aa10\",\n    \"title\":\"Ração Golden Special Sabor Frango e Carne para Cães Adultos\",\n    \"category\":\"food\",\n    \"description\":\"<p>- Indicado para cães adultos;<br>- Livre de corantes e aromatizantes artificiais;<br>- Alimento rico em nutrientes;<br>- Promove o equilíbrio intestinal;<br>- Protege as articulações;<br>- Disponível em embalagens de 15kg e 20kg.</p>\",\n    \"price\":10490,\n    \"images\":[\"https://images.petz.com.br/fotos/1658429301983.jpg\"]\n  },\n  {\n    \"_id\":\"481598b848f447b4b923ca2ad405aa11\",\n    \"title\":\"Ração Royal Canin Golden Retriever - Cães Adultos - 12kg\",\n    \"category\":\"food\",\n    \"description\":\"<p>- Indicada para cães adultos; <br>- Específica para pets da raça Golden Retriever; <br>- Auxilia na manutenção do peso ideal; <br>- Mantém a saúde da musculatura cardíaca; <br>- Proporciona uma pele e pelagem mais saudáveis,<br>- Disponível em embalagem de 12kg. </p>\",\n    \"price\":21999,\n    \"images\":[\"https://images.petz.com.br/fotos/1660146020922.jpg\"]\n  }\n]",
          "latency": 2000,
          "statusCode": 200,
          "label": "Retorna uma lista detalhada de todos produtos cadastrados",
          "headers": [],
          "bodyType": "INLINE",
          "filePath": "",
          "databucketID": "",
          "sendFileAsBody": false,
          "rules": [],
          "rulesOperator": "OR",
          "disableTemplating": false,
          "fallbackTo404": true,
          "default": true,
          "crudKey": "id"
        }
      ],
      "enabled": true,
      "responseMode": null
    }
  ],
  "rootChildren": [
    {
      "type": "route",
      "uuid": "3449e9cb-a3ab-44dc-9ec2-2ebdbbeef066"
    }
  ],
  "proxyMode": false,
  "proxyHost": "",
  "proxyRemovePrefix": false,
  "tlsOptions": {
    "enabled": false,
    "type": "CERT",
    "pfxPath": "",
    "certPath": "",
    "keyPath": "",
    "caPath": "",
    "passphrase": ""
  },
  "cors": true,
  "headers": [
    {
      "key": "Content-Type",
      "value": "application/json"
    },
    {
      "key": "Access-Control-Allow-Origin",
      "value": "*"
    },
    {
      "key": "Access-Control-Allow-Methods",
      "value": "GET,POST,PUT,PATCH,DELETE,HEAD,OPTIONS"
    },
    {
      "key": "Access-Control-Allow-Headers",
      "value": "Content-Type, Origin, Accept, Authorization, Content-Length, X-Requested-With"
    }
  ],
  "proxyReqHeaders": [
    {
      "key": "",
      "value": ""
    }
  ],
  "proxyResHeaders": [
    {
      "key": "",
      "value": ""
    }
  ],
  "data": []
}